README
setup.py
datashaping/__init__.py
datashaping/aggregates.py
datashaping/document.py
datashaping/query.py
datashaping/shaping.py
datashaping.egg-info/PKG-INFO
datashaping.egg-info/SOURCES.txt
datashaping.egg-info/dependency_links.txt
datashaping.egg-info/top_level.txt
datashaping/storage/__init__.py
datashaping/storage/base.py
datashaping/storage/memory.py
datashaping/utils/__init__.py
datashaping/utils/iterators.py
tests/__init__.py
tests/aggregates.py
tests/query.py
tests/shaping.py
tests/storage/__init__.py
tests/storage/memory.py
tests/utils/__init__.py
tests/utils/iterators.py